Flask_Ask-0.9.6.dist-info/DESCRIPTION.rst
Flask_Ask-0.9.6.dist-info/METADATA
Flask_Ask-0.9.6.dist-info/RECORD
Flask_Ask-0.9.6.dist-info/WHEEL
Flask_Ask-0.9.6.dist-info/metadata.json
Flask_Ask-0.9.6.dist-info/top_level.txt
flask_ask/__init__.py
flask_ask/cache.py
flask_ask/convert.py
flask_ask/core.py
flask_ask/models.py
flask_ask/verifier.py
