Metadata-Version: 1.1
Name: Flask-Ask
Version: 0.9.6
Summary: Rapid Alexa Skills Kit Development for Amazon Echo Devices in Python
Home-page: https://github.com/johnwheeler/flask-ask
Author: John Wheeler
Author-email: john@johnwheeler.org
License: Apache 2.0
Platform: any
Classifier: License :: OSI Approved :: Apache Software License
Classifier: Framework :: Flask
Classifier: Programming Language :: Python
Classifier: Environment :: Web Environment
Classifier: Intended Audience :: Developers
Classifier: Operating System :: OS Independent
Classifier: Topic :: Internet :: WWW/HTTP :: Dynamic Content
Classifier: Topic :: Software Development :: Libraries :: Python Modules
